dynamic_beast/__init__.py
dynamic_beast/__main__.py
dynamic_beast/main.py
dynamic_beast-1.8.2.dist-info/entry_points.txt
dynamic_beast-1.8.2.dist-info/WHEEL
dynamic_beast-1.8.2.dist-info/METADATA
dynamic_beast-1.8.2.dist-info/RECORD
