Metadata-Version: 2.1
Name: dynamic-beast
Version: 1.8.2
Summary: 
Author: Wytamma Wirth
Author-email: wytamma.wirth@me.com
Requires-Python: >=3.6.2,<4.0
Classifier: Programming Language :: Python :: 3
Classifier: Programming Language :: Python :: 3.10
Classifier: Programming Language :: Python :: 3.7
Classifier: Programming Language :: Python :: 3.8
Classifier: Programming Language :: Python :: 3.9
Requires-Dist: typer[all] (>=0.3.2)
